ducvannguyen/__init__.py
ducvannguyen/core.py
ducvannguyen-7.0.0.dist-info/METADATA
ducvannguyen-7.0.0.dist-info/WHEEL
ducvannguyen-7.0.0.dist-info/top_level.txt
ducvannguyen-7.0.0.dist-info/RECORD
