Metadata-Version: 2.4
Name: ducvannguyen
Version: 7.0.0
Summary: Professional Python toolkit with advanced utilities and DucVanNguyen class
Author-email: Duc Van Nguyen <ducvannguyenhtml@gmail.com>
License: MIT
Project-URL: Homepage, https://github.com/vanducdev/ducvannguyen
Project-URL: Repository, https://github.com/vanducdev/ducvannguyen
Project-URL: Issues, https://github.com/vanducdev/ducvannguyen/issues
Keywords: ducvannguyen,python,package
Classifier: Development Status :: 3 - Alpha
Classifier: Intended Audience :: Developers
Classifier: License :: OSI Approved :: MIT License
Classifier: Programming Language :: Python :: 3
Classifier: Programming Language :: Python :: 3.7
Classifier: Programming Language :: Python :: 3.8
Classifier: Programming Language :: Python :: 3.9
Classifier: Programming Language :: Python :: 3.10
Classifier: Programming Language :: Python :: 3.11
Classifier: Programming Language :: Python :: 3.12
Requires-Python: >=3.7
